LICENSE
MANIFEST.in
README.md
setup.py
htpasswd/__init__.py
htpasswd/basic.py
htpasswd/group.py
htpasswd.egg-info/PKG-INFO
htpasswd.egg-info/SOURCES.txt
htpasswd.egg-info/dependency_links.txt
htpasswd.egg-info/requires.txt
htpasswd.egg-info/top_level.txt